gitlab_trace.py
gitlab_trace-0.8.0.dist-info/licenses/LICENSE
gitlab_trace-0.8.0.dist-info/METADATA
gitlab_trace-0.8.0.dist-info/WHEEL
gitlab_trace-0.8.0.dist-info/entry_points.txt
gitlab_trace-0.8.0.dist-info/top_level.txt
gitlab_trace-0.8.0.dist-info/RECORD
